jax_random_projections/__init__.py
jax_random_projections/sparse.py
jax_random_projections-1.0.1.dist-info/LICENSE.txt
jax_random_projections-1.0.1.dist-info/METADATA
jax_random_projections-1.0.1.dist-info/WHEEL
jax_random_projections-1.0.1.dist-info/top_level.txt
jax_random_projections-1.0.1.dist-info/RECORD
