Metadata-Version: 2.1
Name: jax-random-projections
Version: 1.0.1
Summary: sklearn's random projection with JAX to run on a GPU
Home-page: https://github.com/Baschdl/jax-random_projections
Author: Sebastian Bischoff
Author-email: sebastian@salzreute.de
License: MIT
Download-URL: https://github.com/Baschdl/jax-random_projections/archive/v1.0.1.tar.gz
Keywords: random projections,jax,GPU
Platform: UNKNOWN
Classifier: Development Status :: 5 - Production/Stable
Classifier: Intended Audience :: Science/Research
Classifier: Intended Audience :: Developers
Classifier: Topic :: Software Development
Classifier: Topic :: Scientific/Engineering
Classifier: License :: OSI Approved :: MIT License
Classifier: Programming Language :: Python :: 3
Classifier: Programming Language :: Python :: 3.6
Classifier: Programming Language :: Python :: 3.7
Classifier: Programming Language :: Python :: 3.8
Classifier: Environment :: GPU
Requires-Dist: sklearn
Requires-Dist: jaxlib
Requires-Dist: jax
